{
  "name": "游戏驿站",
  "ticker": "GME",
  "market": "US",
  "philosophies": [
    "business_model",
    "stop_doing"
  ],
  "opinion_count": 5,
  "bullish_count": 3,
  "bearish_count": 2,
  "preview_opinions": [
    {
      "id": "6562eab0-1171-42da-9bda-b34f550efc15",
      "stock": "游戏驿站",
      "ticker": "GME",
      "market": "US",
      "date": "2021-01-31",
      "sentiment": "bearish",
      "summary": "认为GME股价疯狂",
      "quote": "今天卖了100个下个礼拜五到期的naked call，strike price 800, 收了40多块一个。人们疯了吗？",
      "source_file": "2021-01_batch000",
      "source_type": "xueqiu",
      "chunk_index": 0,
      "url": "https://xueqiu.com/1247347556/170438310"
    },
    {
      "id": "b40b4d5d-e31c-48ad-9a00-0e4fbe8217cd",
      "stock": "GameStop",
      "ticker": "GME",
      "market": "US",
      "date": "2021-02-25",
      "sentiment": "bearish",
      "summary": "卖出看涨期权",
      "quote": "我就不信gme明天能到800块，又卖了明天到期的800块钱的call，收了2块多钱一个。",
      "source_file": "2021-02_batch000",
      "source_type": "xueqiu",
      "chunk_index": 0,
      "url": "https://xueqiu.com/1247347556/172811509"
    },
    {
      "id": "c4ef2fa0-f6a7-4895-9d9d-7adf0517dac1",
      "stock": "游戏驿站",
      "ticker": "GME",
      "market": "US",
      "date": "2024-06-04",
      "sentiment": "bullish",
      "summary": "参与一下留念",
      "quote": "参与一下，留个“记”念。",
      "source_file": "2024-06_batch020",
      "source_type": "xueqiu",
      "chunk_index": 20,
      "url": "https://xueqiu.com/1247347556/292475125"
    }
  ],
  "opinions": [
    {
      "id": "6562eab0-1171-42da-9bda-b34f550efc15",
      "stock": "游戏驿站",
      "ticker": "GME",
      "market": "US",
      "date": "2021-01-31",
      "sentiment": "bearish",
      "summary": "认为GME股价疯狂",
      "quote": "今天卖了100个下个礼拜五到期的naked call，strike price 800, 收了40多块一个。人们疯了吗？",
      "source_file": "2021-01_batch000",
      "source_type": "xueqiu",
      "chunk_index": 0,
      "url": "https://xueqiu.com/1247347556/170438310"
    },
    {
      "id": "b40b4d5d-e31c-48ad-9a00-0e4fbe8217cd",
      "stock": "GameStop",
      "ticker": "GME",
      "market": "US",
      "date": "2021-02-25",
      "sentiment": "bearish",
      "summary": "卖出看涨期权",
      "quote": "我就不信gme明天能到800块，又卖了明天到期的800块钱的call，收了2块多钱一个。",
      "source_file": "2021-02_batch000",
      "source_type": "xueqiu",
      "chunk_index": 0,
      "url": "https://xueqiu.com/1247347556/172811509"
    },
    {
      "id": "c4ef2fa0-f6a7-4895-9d9d-7adf0517dac1",
      "stock": "游戏驿站",
      "ticker": "GME",
      "market": "US",
      "date": "2024-06-04",
      "sentiment": "bullish",
      "summary": "参与一下留念",
      "quote": "参与一下，留个“记”念。",
      "source_file": "2024-06_batch020",
      "source_type": "xueqiu",
      "chunk_index": 20,
      "url": "https://xueqiu.com/1247347556/292475125"
    },
    {
      "id": "d2f002fa-fa5c-4a08-8ee6-f88b1c10a620",
      "stock": "游戏驿站",
      "ticker": "GME",
      "market": "US",
      "date": "2024-06-05",
      "sentiment": "bullish",
      "summary": "看涨GME期权交易",
      "quote": "其实这就是慢慢变富的概念，这个call基本上肯定是赚的。...$游戏驿站(GME)$ 参与一下，留个“记”念。",
      "source_file": "2024-06_batch019",
      "source_type": "xueqiu",
      "chunk_index": 19,
      "url": "https://xueqiu.com/1247347556/292683039"
    },
    {
      "id": "14879111-97af-46c5-a270-371a089e3c73",
      "stock": "游戏驿站",
      "ticker": "GME",
      "market": "US",
      "date": "2024-06-08",
      "sentiment": "bullish",
      "summary": "看涨GME，上涨将获利",
      "quote": "“有分析指出，游戏驿站的股价要达到大约105美元及以上，段永平才会亏损”， 那是瞎分析，因为这个股票要是能涨到105以上的话，我最后肯定能赚更多。",
      "source_file": "2024-06_batch016",
      "source_type": "xueqiu",
      "chunk_index": 16,
      "url": "https://xueqiu.com/1247347556/293184437"
    }
  ]
}