[
  {
    "philosophy_key": "corporate_culture",
    "quote": "我从来都是不鼓励加班的，希望你现在的工作没那么累了哈。",
    "post_url": "https://xueqiu.com/1247347556/245689542",
    "post_date": "2023-03-27",
    "mentioned_stocks": [],
    "quality_score": 3
  },
  {
    "philosophy_key": "stop_doing",
    "quote": "我不跟那个谁摔跤，但我看到观点差别很大的我可以拉黑啊，当然他们也可以拉黑我。我只是分享，从来没打算跟谁讨论过。我有足够的经历不想跟任何人讨论问题，对吧？",
    "post_url": "https://xueqiu.com/1247347556/245688260",
    "post_date": "2023-03-27",
    "mentioned_stocks": [],
    "quality_score": 3
  }
]