[
  {
    "philosophy_key": "stop_doing",
    "quote": "对很多常规意义上不会破产的企业，相对投资者来说是会破产的，资产重组，负债化股等，对投资者来说可能都类似破产。现在看来违反了基本规律的，没什么能够避免最终结局。",
    "post_url": "https://xueqiu.com/1247347556/368865894",
    "post_date": "2026-01-03",
    "mentioned_stocks": [
      "万科A"
    ],
    "quality_score": 5
  },
  {
    "philosophy_key": "long_termism",
    "quote": "这是我管的一个账号上的苹果。这么多年几乎没怎么动过，全靠打球赚的钱哈。",
    "post_url": "https://xueqiu.com/1247347556/368798533",
    "post_date": "2026-01-02",
    "mentioned_stocks": [
      "苹果"
    ],
    "quality_score": 5
  },
  {
    "philosophy_key": "circle_of_competence",
    "quote": "新的一年里，需要认真学习一下怎么使用ai，希望能让自己能理解ai到敢下重注的地步。",
    "post_url": "https://xueqiu.com/1247347556/368798533",
    "post_date": "2026-01-02",
    "mentioned_stocks": [],
    "quality_score": 4
  },
  {
    "philosophy_key": "long_termism",
    "quote": "不知道，至少再存五年吧。当年我在99大华买了茅台新酒去测试，自己试了一下以为是假酒，过了好几年才突然想明白那是新酒啊。",
    "post_url": "https://xueqiu.com/1247347556/368757215",
    "post_date": "2026-01-01",
    "mentioned_stocks": [],
    "quality_score": 3
  }
]